setup.cfg
setup.py
hybridSIR/__init__.py
hybridSIR/model_setup.py
hybridSIR/preprocessing.py
hybridSIR.egg-info/PKG-INFO
hybridSIR.egg-info/SOURCES.txt
hybridSIR.egg-info/dependency_links.txt
hybridSIR.egg-info/not-zip-safe
hybridSIR.egg-info/top_level.txt