Metadata-Version: 1.0
Name: hybridSIR
Version: 0.0
Summary: Hybrid version of the SIR model
Home-page: UNKNOWN
Author: UNKNOWN
Author-email: rebeccadavidsson3@gmail.com
License: UNKNOWN
Platform: UNKNOWN
